LICENSE
MANIFEST.in
README.md
README_ja.md
setup.py
examples/led_serial.py
examples/measure_ble.py
examples/measure_serial.py
examples/notify_ble.py
examples/scan_ble.py
omron_2jcie_bu01/__init__.py
omron_2jcie_bu01/ble.py
omron_2jcie_bu01/serial.py
omron_2jcie_bu01.egg-info/PKG-INFO
omron_2jcie_bu01.egg-info/SOURCES.txt
omron_2jcie_bu01.egg-info/dependency_links.txt
omron_2jcie_bu01.egg-info/requires.txt
omron_2jcie_bu01.egg-info/top_level.txt
test/test_connect.py
test/test_notify.py
test/test_scan.py
test/test_serial.py