Metadata-Version: 2.1
Name: omron-2jcie-bu01
Version: 0.1.0
Summary: API for OMRON 2JCIE-BU01 Environment Sensor
Home-page: https://github.com/nobrin/omron-2jcie-bu01
Author: Nobuo Okazaki
Author-email: nobrin@biokids.org
License: MIT
Platform: any
Classifier: Development Status :: 3 - Alpha
Classifier: Intended Audience :: Developers
Classifier: License :: OSI Approved :: MIT License
Classifier: Topic :: Home Automation
Classifier: Topic :: System :: Hardware
Classifier: Programming Language :: Python :: 3.6
Classifier: Programming Language :: Python :: 3.7
Classifier: Programming Language :: Python :: 3.8
Provides-Extra: ble
